<?xml version="1.0" encoding="UTF-8"?>
<Image>
  <ObservationId>14404</ObservationId>
  <MediaId>80479</MediaId>
  <Vote>4</Vote>
  <Content>Flower</Content>
  <ClassId>30162</ClassId>
  <Family>Orchidaceae</Family>
  <Genus>Himantoglossum</Genus>
  <Species>Himantoglossum hircinum (L.) Spreng.</Species>
  <Author>esra gauthier</Author>
  <Date>2014-5-20</Date>
  <Location>Puylaurens</Location>
  <Latitude>43.55541</Latitude>
  <Longitude>2.004</Longitude>
  <YearInCLEF>PlantCLEF2015</YearInCLEF>
  <ObservationId2014 />
  <ImageId2014 />
  <LearnTag>Train</LearnTag>
</Image>
